amazon_datazone_mcp_server/__init__.py
amazon_datazone_mcp_server/py.typed
amazon_datazone_mcp_server/server.py
amazon_datazone_mcp_server/tools/__init__.py
amazon_datazone_mcp_server/tools/common.py
amazon_datazone_mcp_server/tools/data_management.py
amazon_datazone_mcp_server/tools/domain_management.py
amazon_datazone_mcp_server/tools/environment.py
amazon_datazone_mcp_server/tools/glossary.py
amazon_datazone_mcp_server/tools/project_management.py
amazon_datazone_mcp_server-0.1.1.dist-info/licenses/LICENSE
amazon_datazone_mcp_server-0.1.1.dist-info/licenses/NOTICE
amazon_datazone_mcp_server-0.1.1.dist-info/METADATA
amazon_datazone_mcp_server-0.1.1.dist-info/WHEEL
amazon_datazone_mcp_server-0.1.1.dist-info/entry_points.txt
amazon_datazone_mcp_server-0.1.1.dist-info/top_level.txt
amazon_datazone_mcp_server-0.1.1.dist-info/RECORD
