Metadata-Version: 2.4
Name: amazon-datazone-mcp-server
Version: 0.1.1
Summary: MCP server for AWS DataZone service - enables LLMs to interact with DataZone for data governance, cataloging, and management
Author-email: AWS Labs <aws-labs@amazon.com>
License-Expression: Apache-2.0
Project-URL: Homepage, https://github.com/awslabs/amazon-datazone-mcp-server
Project-URL: Documentation, https://github.com/awslabs/amazon-datazone-mcp-server/blob/main/docs/
Project-URL: Repository, https://github.com/awslabs/amazon-datazone-mcp-server
Project-URL: Issues, https://github.com/awslabs/amazon-datazone-mcp-server/issues
Project-URL: Changelog, https://github.com/awslabs/amazon-datazone-mcp-server/blob/main/CHANGELOG.md
Keywords: aws,datazone,mcp,model-context-protocol,data-governance,data-catalog
Classifier: Development Status :: 4 - Beta
Classifier: Intended Audience :: Developers
Classifier: Programming Language :: Python :: 3
Classifier: Programming Language :: Python :: 3.10
Classifier: Programming Language :: Python :: 3.11
Classifier: Programming Language :: Python :: 3.12
Classifier: Topic :: Software Development :: Libraries :: Python Modules
Classifier: Topic :: Database
Classifier: Topic :: Software Development :: Code Generators
Classifier: Environment :: Console
Requires-Python: >=3.10
License-File: LICENSE
License-File: NOTICE
Requires-Dist: boto3>=1.26.0
Requires-Dist: mcp>=1.9.2
Requires-Dist: pydantic>=2.0.0
Requires-Dist: httpx>=0.24.0
Provides-Extra: dev
Requires-Dist: pytest>=7.0.0; extra == "dev"
Requires-Dist: pytest-cov>=4.0.0; extra == "dev"
Requires-Dist: pytest-asyncio>=1.1.0; extra == "dev"
Requires-Dist: black>=23.0.0; extra == "dev"
Requires-Dist: isort>=5.12.0; extra == "dev"
Requires-Dist: mypy>=1.0.0; extra == "dev"
Requires-Dist: flake8>=6.0.0; extra == "dev"
Requires-Dist: pre-commit>=3.0.0; extra == "dev"
Requires-Dist: pyright>=1.1.350; extra == "dev"
Requires-Dist: ruff>=0.4.4; extra == "dev"
Dynamic: license-file
